README.txt
setup.py
collective/__init__.py
collective.types.externalsearch.egg-info/PKG-INFO
collective.types.externalsearch.egg-info/SOURCES.txt
collective.types.externalsearch.egg-info/dependency_links.txt
collective.types.externalsearch.egg-info/entry_points.txt
collective.types.externalsearch.egg-info/namespace_packages.txt
collective.types.externalsearch.egg-info/not-zip-safe
collective.types.externalsearch.egg-info/requires.txt
collective.types.externalsearch.egg-info/top_level.txt
collective/types/__init__.py
collective/types/externalsearch/TODO.txt
collective/types/externalsearch/__init__.py
collective/types/externalsearch/config.py
collective/types/externalsearch/configure.zcml
collective/types/externalsearch/interfaces.py
collective/types/externalsearch/setuphandlers.py
collective/types/externalsearch/skins.zcml
collective/types/externalsearch/version.txt
collective/types/externalsearch/Extensions/Install.py
collective/types/externalsearch/Extensions/__init__.py
collective/types/externalsearch/browser/__init__.py
collective/types/externalsearch/browser/collage.pt
collective/types/externalsearch/browser/collage.py
collective/types/externalsearch/browser/collage.zcml
collective/types/externalsearch/browser/configure.zcml
collective/types/externalsearch/browser/external_search.pt
collective/types/externalsearch/browser/external_search.py
collective/types/externalsearch/browser/externalsearch_icon.gif
collective/types/externalsearch/browser/page_wrapper.pt
collective/types/externalsearch/browser/page_wrapper.py
collective/types/externalsearch/browser/topic_cte_inline.pt
collective/types/externalsearch/browser/util.py
collective/types/externalsearch/content/__init__.py
collective/types/externalsearch/content/configure.zcml
collective/types/externalsearch/content/externalsearch.py
collective/types/externalsearch/profiles/default/collective.types.externalsearch_various.txt
collective/types/externalsearch/profiles/default/factorytool.xml
collective/types/externalsearch/profiles/default/import_steps.xml
collective/types/externalsearch/profiles/default/metadata.xml
collective/types/externalsearch/profiles/default/skins.xml
collective/types/externalsearch/profiles/default/types.xml
collective/types/externalsearch/profiles/default/types/collective.types.ExternalSearch.xml
collective/types/externalsearch/skins/cte_templates/folder_listing_cte_inline.pt
collective/types/externalsearch/tests/__init__.py
