Metadata-Version: 1.0
Name: collective.types.externalsearch
Version: 11.04
Summary: External searches in Plone
Home-page: http://svn.plone.org/svn/collective/collective.types.externalsearch/
Author: Liz Dahlstrom
Author-email: lhill2@u.washington.edu
License: GPL
Keywords: plone types search google
Platform: UNKNOWN
Classifier: Framework :: Plone
Classifier: Framework :: Zope2
Classifier: Programming Language :: Python
Classifier: Topic :: Software Development :: Libraries :: Python Modules
